robflask/__init__.py
robflask/config.py
robflask/error.py
robflask/service.py
robflask/version.py
robflask/api/__init__.py
robflask/api/benchmark.py
robflask/api/files.py
robflask/api/run.py
robflask/api/server.py
robflask/api/submission.py
robflask/api/ui.py
robflask/api/user.py
robflask/api/util.py
robflask/tests/__init__.py
robflask/tests/user.py
rob_flask-0.6.0.dist-info/LICENSE
rob_flask-0.6.0.dist-info/METADATA
rob_flask-0.6.0.dist-info/WHEEL
rob_flask-0.6.0.dist-info/top_level.txt
rob_flask-0.6.0.dist-info/RECORD
