Metadata-Version: 2.1
Name: rob-flask
Version: 0.6.0
Summary: Reproducible Open Benchmarks - Flask Web API
Home-page: https://github.com/scailfin/rob-webapi-flask
Author: Heiko Mueller
Author-email: heiko.muller@gmail.com
License: MIT
Keywords: reproducibility benchmarks data-analysis webapi
Platform: UNKNOWN
Classifier: License :: OSI Approved :: MIT License
Classifier: Operating System :: OS Independent
Classifier: Programming Language :: Python :: 2
Classifier: Programming Language :: Python :: 2.7
Classifier: Programming Language :: Python :: 3
Classifier: Programming Language :: Python :: 3.6
Classifier: Programming Language :: Python :: 3.7
Classifier: Programming Language :: Python
Requires-Dist: flowserv-core (>=0.7.1)
Requires-Dist: flask
Requires-Dist: flask-cors
Provides-Extra: dev
Requires-Dist: flake8 ; extra == 'dev'
Requires-Dist: python-language-server ; extra == 'dev'
Requires-Dist: coverage (>=4.0) ; extra == 'dev'
Requires-Dist: pytest ; extra == 'dev'
Requires-Dist: pytest-cov ; extra == 'dev'
Requires-Dist: tox ; extra == 'dev'
Provides-Extra: docs
Requires-Dist: Sphinx ; extra == 'docs'
Requires-Dist: sphinx-rtd-theme ; extra == 'docs'
Provides-Extra: tests
Requires-Dist: coverage (>=4.0) ; extra == 'tests'
Requires-Dist: pytest ; extra == 'tests'
Requires-Dist: pytest-cov ; extra == 'tests'
Requires-Dist: tox ; extra == 'tests'
